<Template>
  <WidgetGroup>
    <ObjectName>Topbar</ObjectName>
    <Layout>vertical</Layout>
    <Size>0me,75f</Size>
    <Children>
      <WidgetGroup>
        <ObjectName>Topbar_Info</ObjectName>
        <Layout>horizontal</Layout>
        <Children>
          <Time>
            <TooltipId>time</TooltipId>
            <ObjectName>Clock</ObjectName>
          </Time>
          <Label>
            <Text>Debug value:</Text>
          </Label>
          <Key>
            <Connection>
              <ConfigKey>[Channel1],LoadSelectedTrack</ConfigKey>
            </Connection>
          </Key>
        </Children>
      </WidgetGroup>
      <WidgetGroup>
        <ObjectName>TabControls</ObjectName>
        <Layout>horizontal</Layout>
        <SizePolicy>me,me</SizePolicy>
        <Children>
          <Template src="skin:tab.xml">
            <SetVariable name="tab_name">Overview</SetVariable>
            <SetVariable name="config_key">overview</SetVariable>
          </Template>
          <Template src="skin:tab.xml">
            <SetVariable name="tab_name">Browse</SetVariable>
            <SetVariable name="config_key">library</SetVariable>
          </Template>
          <Template src="skin:tab.xml">
            <SetVariable name="tab_name">Effects/Samples</SetVariable>
            <SetVariable name="config_key">effects_samples</SetVariable>
          </Template>
        </Children>
      </WidgetGroup>
    </Children>
  </WidgetGroup>
</Template>
